mullet/__init__.py
mullet/_version.py
mullet/utils.py
mullet-0.1.0.dist-info/METADATA
mullet-0.1.0.dist-info/WHEEL
mullet-0.1.0.dist-info/top_level.txt
mullet-0.1.0.dist-info/RECORD
