Metadata-Version: 2.1
Name: mullet
Version: 0.1.0
Summary: Model for the evalUation of sea-LeveL risE and Temperature (MULLET), currently a playground for exploring simple climate model setups.
Home-page: https://github.com/znicholls/mullet
Author: Zebedee Nicholls
Author-email: zebedee.nicholls@climate-energy-college.org
License: 3-Clause BSD License
Keywords: mullet,python,fortran,simple,climate,model
Platform: UNKNOWN
Classifier: Development Status :: 4 - Beta
Classifier: License :: OSI Approved :: BSD License
Classifier: Intended Audience :: Developers
Classifier: Operating System :: OS Independent
Classifier: Programming Language :: Python :: 3.6
Classifier: Programming Language :: Python :: 3.7
Requires-Dist: numpy
Requires-Dist: scipy
Provides-Extra: deploy
Requires-Dist: twine (>=1.11.0) ; extra == 'deploy'
Requires-Dist: setuptools (>=38.6.0) ; extra == 'deploy'
Requires-Dist: wheel (>=0.31.0) ; extra == 'deploy'
Provides-Extra: dev
Requires-Dist: bandit ; extra == 'dev'
Requires-Dist: black ; extra == 'dev'
Requires-Dist: flake8 ; extra == 'dev'
Requires-Dist: isort ; extra == 'dev'
Requires-Dist: mypy ; extra == 'dev'
Requires-Dist: pydocstyle ; extra == 'dev'
Requires-Dist: pylint (>=2.4.4) ; extra == 'dev'
Requires-Dist: twine (>=1.11.0) ; extra == 'dev'
Requires-Dist: setuptools (>=38.6.0) ; extra == 'dev'
Requires-Dist: wheel (>=0.31.0) ; extra == 'dev'
Requires-Dist: sphinx (>=1.4) ; extra == 'dev'
Requires-Dist: sphinx-rtd-theme ; extra == 'dev'
Requires-Dist: ipywidgets ; extra == 'dev'
Requires-Dist: notebook ; extra == 'dev'
Requires-Dist: pandas ; extra == 'dev'
Requires-Dist: seaborn ; extra == 'dev'
Requires-Dist: tqdm ; extra == 'dev'
Requires-Dist: codecov ; extra == 'dev'
Requires-Dist: coverage ; extra == 'dev'
Requires-Dist: nbval ; extra == 'dev'
Requires-Dist: pytest-cov ; extra == 'dev'
Requires-Dist: pytest (>=4.0) ; extra == 'dev'
Provides-Extra: docs
Requires-Dist: sphinx (>=1.4) ; extra == 'docs'
Requires-Dist: sphinx-rtd-theme ; extra == 'docs'
Provides-Extra: notebooks
Requires-Dist: ipywidgets ; extra == 'notebooks'
Requires-Dist: notebook ; extra == 'notebooks'
Requires-Dist: pandas ; extra == 'notebooks'
Requires-Dist: seaborn ; extra == 'notebooks'
Requires-Dist: tqdm ; extra == 'notebooks'
Provides-Extra: tests
Requires-Dist: codecov ; extra == 'tests'
Requires-Dist: coverage ; extra == 'tests'
Requires-Dist: nbval ; extra == 'tests'
Requires-Dist: pytest-cov ; extra == 'tests'
Requires-Dist: pytest (>=4.0) ; extra == 'tests'
